README.rst
fuzzify.py
setup.py
fuzzify.egg-info/PKG-INFO
fuzzify.egg-info/SOURCES.txt
fuzzify.egg-info/dependency_links.txt
fuzzify.egg-info/entry_points.txt
fuzzify.egg-info/requires.txt
fuzzify.egg-info/top_level.txt